vendorpromo/__init__.py
vendorpromo/__version__.py
vendorpromo/admin.py
vendorpromo/apps.py
vendorpromo/config.py
vendorpromo/forms.py
vendorpromo/integrations.py
vendorpromo/mixins.py
vendorpromo/models.py
vendorpromo/urls.py
vendorpromo/utils.py
vendorpromo/views.py
vendorpromo/api/__init__.py
vendorpromo/api/v1/__init__.py
vendorpromo/api/v1/urls.py
vendorpromo/api/v1/views.py
vendorpromo/api/v1/vouchery/__init__.py
vendorpromo/api/v1/vouchery/urls.py
vendorpromo/api/v1/vouchery/views.py
vendorpromo/migrations/0001_initial.py
vendorpromo/migrations/0002_affiliate_couponcode_promotionalcampaign.py
vendorpromo/migrations/0003_auto_20230524_1701.py
vendorpromo/migrations/0004_affiliate_name_type.py
vendorpromo/migrations/0005_alter_couponcode_code.py
vendorpromo/migrations/__init__.py
vendorpromo/processors/DummyProcessor.py
vendorpromo/processors/__init__.py
vendorpromo/processors/base.py
vendorpromo/processors/stripe.py
vendorpromo/processors/vouchery.py
vendorpromo/templates/vendorpromo/affiliate_detail.html
vendorpromo/templates/vendorpromo/affiliate_list.html
vendorpromo/templates/vendorpromo/base.html
vendorpromo/templates/vendorpromo/coupon_code_detail.html
vendorpromo/templates/vendorpromo/coupon_code_list.html
vendorpromo/templates/vendorpromo/processor_site_config.html
vendorpromo/templates/vendorpromo/processor_site_config_list.html
vendorpromo/templates/vendorpromo/promo.html
vendorpromo/templates/vendorpromo/promo_list.html
vendorpromo/templates/vendorpromo/promocode_formset.html
vendorpromo/templates/vendorpromo/promotional_campaign_detail.html
vendorpromo/templates/vendorpromo/promotional_campaign_list.html
vendorpromo/templates/vendorpromo/vouchery_detail.html
vendorpromo/templates/vendorpromo/vouchery_integration.html
vendorpromo/templates/vendorpromo/vouchery_list.html
vendorpromo/templates/vendorpromo/includes/promocode_apply.html
vendorpromo/tests/__init__.py
vendorpromo/tests/test_affiliate.py
vendorpromo/tests/test_api.py
django_vendor_promo-0.2.12.dist-info/LICENSE.mit.txt
django_vendor_promo-0.2.12.dist-info/METADATA
django_vendor_promo-0.2.12.dist-info/WHEEL
django_vendor_promo-0.2.12.dist-info/top_level.txt
django_vendor_promo-0.2.12.dist-info/RECORD
